{
  "type": "minecraft:entity",
  "pools": [
    {
      "rolls": 1.0,
      "entries": [
        {
          "type": "minecraft:item",
          "name": "minecraft:command_block",
          "weight": 1,
          "functions": [
            {
              "function": "minecraft:set_nbt",
              "tag": "{display:{Name:'{\"text\":\"Broodmother\\'s Web\",\"color\":\"#C2B3A4\",\"italic\":false}'},CustomModelData:10000075,broodmothers_web:1,float:1,BlockEntityTag:{id:\"minecraft:command_block\",Command:\"setblock ~ ~ ~ air\",auto:1b}}"
            }
          ],
          "conditions": [
            {
              "condition": "minecraft:killed_by_player"
            }
          ]
        }
      ]
    },
    {
      "rolls": 5.0,
      "entries": [
        {
          "type": "minecraft:item",
          "name": "minecraft:fermented_spider_eye",
          "weight": 3,
          "functions": [
            {
              "function": "minecraft:set_count",
              "count": {
                "min": 1.0,
                "max": 3.0,
                "type": "minecraft:uniform"
              }
            }
          ],
          "conditions": [
            {
              "condition": "minecraft:random_chance",
              "chance": 0.75
            }
          ]
        },
        {
          "type": "minecraft:item",
          "name": "minecraft:string",
          "weight": 5,
          "functions": [
            {
              "function": "minecraft:set_count",
              "count": {
                "min": 4.0,
                "max": 17.0,
                "type": "minecraft:uniform"
              }
            }
          ],
          "conditions": [
            {
              "condition": "minecraft:random_chance",
              "chance": 0.95
            }
          ]
        },
        {
          "type": "minecraft:item",
          "name": "minecraft:cobweb",
          "weight": 2,
          "functions": [
            {
              "function": "minecraft:set_count",
              "count": {
                "min": 1.0,
                "max": 5.0,
                "type": "minecraft:uniform"
              }
            }
          ],
          "conditions": [
            {
              "condition": "minecraft:random_chance",
              "chance": 0.7
            }
          ]
        },
        {
          "type": "minecraft:item",
          "name": "minecraft:white_wool",
          "weight": 1,
          "functions": [
            {
              "function": "minecraft:set_count",
              "count": {
                "min": 1.0,
                "max": 8.0,
                "type": "minecraft:uniform"
              }
            }
          ],
          "conditions": [
            {
              "condition": "minecraft:random_chance",
              "chance": 0.5
            }
          ]
        }
      ]
    },
    {
      "rolls": 1.0,
      "entries": [
        {
          "type": "minecraft:item",
          "name": "minecraft:command_block",
          "weight": 1,
          "functions": [
            {
              "function": "minecraft:set_nbt",
              "tag": "{display:{Name:'{\"text\":\"Moon Crystal\",\"color\":\"#D18DD9\",\"italic\":false}'},CustomModelData:10000002,moon_crystal:1,float:1,BlockEntityTag:{id:\"minecraft:command_block\",Command:\"setblock ~ ~ ~ air\",auto:1b}}"
            },
            {
              "function": "minecraft:set_count",
              "count": {
                "min": 9.0,
                "max": 34.0,
                "type": "minecraft:uniform"
              }
            }
          ]
        }
      ]
    },
    {
      "rolls": 25.0,
      "entries": [
        {
          "type": "minecraft:item",
          "name": "minecraft:lime_dye",
          "weight": 1,
          "functions": [
            {
              "function": "minecraft:set_nbt",
              "tag": "{display:{Name:'{\"text\":\"Experience\",\"color\":\"#00FF00\",\"italic\":false}'},experience:1}"
            }
          ],
          "conditions": [
            {
              "condition": "minecraft:random_chance",
              "chance": 0.75
            }
          ]
        }
      ]
    }
  ]
}